odoo/addons/maintenance_equipment_scrap/README.rst
odoo/addons/maintenance_equipment_scrap/__init__.py
odoo/addons/maintenance_equipment_scrap/__manifest__.py
odoo/addons/maintenance_equipment_scrap/data/maintenance_data.xml
odoo/addons/maintenance_equipment_scrap/models/__init__.py
odoo/addons/maintenance_equipment_scrap/models/maintenance_equipment.py
odoo/addons/maintenance_equipment_scrap/models/maintenance_equipment_category.py
odoo/addons/maintenance_equipment_scrap/readme/CONTRIBUTORS.rst
odoo/addons/maintenance_equipment_scrap/readme/DESCRIPTION.rst
odoo/addons/maintenance_equipment_scrap/static/description/icon.png
odoo/addons/maintenance_equipment_scrap/static/description/index.html
odoo/addons/maintenance_equipment_scrap/tests/__init__.py
odoo/addons/maintenance_equipment_scrap/tests/test_maintenance_equipment_scrap.py
odoo/addons/maintenance_equipment_scrap/views/maintenance_equipment.xml
odoo/addons/maintenance_equipment_scrap/views/maintenance_equipment_category.xml
odoo/addons/maintenance_equipment_scrap/wizard/__init__.py
odoo/addons/maintenance_equipment_scrap/wizard/scrap_equipment.py
odoo/addons/maintenance_equipment_scrap/wizard/scrap_equipment.xml
odoo11_addon_maintenance_equipment_scrap-11.0.1.0.0.dist-info/METADATA
odoo11_addon_maintenance_equipment_scrap-11.0.1.0.0.dist-info/RECORD
odoo11_addon_maintenance_equipment_scrap-11.0.1.0.0.dist-info/WHEEL
odoo11_addon_maintenance_equipment_scrap-11.0.1.0.0.dist-info/top_level.txt
